swagger_sdk/__init__.py
swagger_sdk/builder.py
swagger_sdk/config.py
swagger_sdk/dataclass_parser.py
swagger_sdk/decorators.py
swagger_sdk/docstring_parser.py
swagger_sdk/enums.py
swagger_sdk/exceptions.py
swagger_sdk/html_generator.py
swagger_sdk/json_generator.py
swagger_sdk/logger.py
swagger_sdk/models.py
swagger_sdk/preview.py
swagger_sdk/scanner.py
swagger_sdk/type_parser.py
swagger_sdk/validator.py
swagger_sdk/yaml_generator.py
swagger_sdk-0.1.0.dist-info/licenses/LICENSE
swagger_sdk-0.1.0.dist-info/METADATA
swagger_sdk-0.1.0.dist-info/WHEEL
swagger_sdk-0.1.0.dist-info/top_level.txt
swagger_sdk-0.1.0.dist-info/RECORD
