Metadata-Version: 2.4
Name: swagger-sdk
Version: 0.1.0
Summary: 一个独立、灵活的 Python SDK，用于自动生成符合 OpenAPI 3.0 规范的 Swagger 文档
Home-page: https://github.com/AndsGo/swagger-sdk
Author: songxulin
Author-email: songxulin <songandco99@gmail.com>
License: MIT
Project-URL: Homepage, https://github.com/AndsGo/swagger-sdk
Project-URL: Documentation, https://github.com/AndsGo/swagger-sdk#readme
Project-URL: Repository, https://github.com/AndsGo/swagger-sdk
Project-URL: Issues, https://github.com/AndsGo/swagger-sdk/issues
Keywords: swagger,openapi,api,documentation,openapi3,swagger-ui
Classifier: Development Status :: 4 - Beta
Classifier: Intended Audience :: Developers
Classifier: License :: OSI Approved :: MIT License
Classifier: Operating System :: OS Independent
Classifier: Programming Language :: Python :: 3
Classifier: Programming Language :: Python :: 3.8
Classifier: Programming Language :: Python :: 3.9
Classifier: Programming Language :: Python :: 3.10
Classifier: Programming Language :: Python :: 3.11
Classifier: Programming Language :: Python :: 3.12
Classifier: Topic :: Software Development :: Libraries :: Python Modules
Classifier: Topic :: Documentation
Classifier: Topic :: Internet :: WWW/HTTP :: HTTP Servers
Requires-Python: >=3.8
License-File: LICENSE
Provides-Extra: dev
Requires-Dist: pytest>=7.0.0; extra == "dev"
Requires-Dist: pytest-cov>=4.0.0; extra == "dev"
Dynamic: author
Dynamic: home-page
Dynamic: license-file
Dynamic: requires-python
